{
  "preRequisites:11": [
    548855362,
    1838549927
  ],
  "properties:10": {
    "betterquesting:10": {
      "desc:8": "",
      "icon:10": {
        "Count:3": 1,
        "id:8": "bhc:blue_heart_canister"
      },
      "name:8": "Blue Heart Canister",
      "visibility:8": "ALWAYS"
    }
  },
  "questID:3": 275332547,
  "tasks:9": {
    "0:10": {
      "index:3": 0,
      "requiredItems:9": {
        "0:10": {
          "Count:3": 1,
          "id:8": "bhc:blue_heart_canister"
        }
      },
      "taskID:8": "bq_standard:retrieval"
    }
  }
}