{
  "preRequisites:11": [
    347
  ],
  "properties:10": {
    "betterquesting:10": {
      "desc:8": "",
      "icon:10": {
        "Count:3": 1,
        "id:8": "twilightforest:lamp_of_cinders"
      },
      "name:8": "Lamp of Cinders",
      "visibility:8": "ALWAYS"
    }
  },
  "questID:3": 389,
  "tasks:9": {
    "0:10": {
      "index:3": 0,
      "requiredItems:9": {
        "0:10": {
          "Count:3": 1,
          "id:8": "twilightforest:lamp_of_cinders"
        }
      },
      "taskID:8": "bq_standard:retrieval"
    }
  }
}